MANIFEST.in
Makefile
Makefile.default
Makefile.guill
Makefile.guill.old
Makefile.skynet3
README.md
rmn_wrapper.c
setup.cfg
setup.py
src/pylibrmn.egg-info/PKG-INFO
src/pylibrmn.egg-info/SOURCES.txt
src/pylibrmn.egg-info/dependency_links.txt
src/pylibrmn.egg-info/top_level.txt
src/rpn/__init__.py
src/rpn/data_types.py
src/rpn/grid_types.py
src/rpn/level_kinds.py
src/rpn/rpn.py
src/rpn/rpn_multi.py
src/rpn/variable.py
src/rpn/domains/__init__.py
src/rpn/domains/gauss_grid.py
src/rpn/domains/lat_lon.py
src/rpn/domains/rotated_lat_lon.py
src/rpn/tests/__init__.py
src/rpn/tests/test_append.py
src/rpn/tests/test_basemap_integration.py
src/rpn/tests/test_copy.py
src/rpn/tests/test_em32_data_type.py
src/rpn/tests/test_get_longitudes_and_latitudes_for_the_last_read_rec.py
src/rpn/tests/test_link_files.py
src/rpn/tests/test_meta.py
src/rpn/tests/test_nclike_interface.py
src/rpn/tests/test_on_skynet3.py
src/rpn/tests/test_read_ts.py
src/rpn/tests/test_record_iterator.py
src/rpn/tests/test_rpn.py
src/rpn/tests/test_write.py
src/rpn/tests/utils.py
src/rpn/tests/data/CRU_interpolado_big
src/rpn/tests/data/G_grid_LOLA.rpn
src/rpn/tests/data/create_G_grid_LOLA.sh
src/rpn/tests/data/erai_1980-2009_PR_ts.88
src/rpn/tests/data/mappe.rpnw
src/rpn/tests/data/metas.rpn
src/rpn/tests/data/test.rpn
src/rpn/tests/data/test_G_grid.rpn
src/rpn/util/__init__.py
src/rpn/util/bash_utils.py
src/rpn/util/polar_stereographic.py
src/rpn_use_examples/__init__.py
src/rpn_use_examples/create_northern_great_plains_mask.py
src/rpn_use_examples/select_records.py
src/rpn_use_examples/set_dateo.py
src/rpn_use_examples/set_level.py
src/rpn_use_examples/snow_depth_and_density.py