Metadata-Version: 1.1
Name: pylibrmn
Version: 1.0.1
Summary: Package for reading and writing RPN files
Home-page: https://github.com/guziy/pylibrmn
Author: huziy
Author-email: guziy.sasha@gmail.com
License: GPL
Keywords: RPN,standard files
Platform: UNKNOWN
Classifier: Programming Language :: Python :: 2.7
Classifier: Programming Language :: Python :: 3.4
Requires: numpy
Requires: nose
